tree_sitter_type_provider/__init__.py
tree_sitter_type_provider/node_types.py
tree_sitter_type_provider/py.typed
tree_sitter_type_provider-2.2.0.dist-info/LICENSE
tree_sitter_type_provider-2.2.0.dist-info/METADATA
tree_sitter_type_provider-2.2.0.dist-info/WHEEL
tree_sitter_type_provider-2.2.0.dist-info/top_level.txt
tree_sitter_type_provider-2.2.0.dist-info/RECORD
