Metadata-Version: 2.1
Name: tree_sitter_type_provider
Version: 2.2.0
Summary: Type providers for tree-sitter in Python.
Author-email: Wen Kokke <wenkokke@users.noreply.github.com>
License: MIT License
Keywords: parser,tree-sitter,type-provider
Classifier: License :: OSI Approved :: MIT License
Classifier: Topic :: Software Development :: Compilers
Classifier: Programming Language :: Python :: 3 :: Only
Classifier: Programming Language :: Python :: 3
Classifier: Programming Language :: Python :: 3.8
Classifier: Programming Language :: Python :: 3.9
Classifier: Programming Language :: Python :: 3.10
Classifier: Programming Language :: Python :: 3.11
Classifier: Programming Language :: Python :: 3.12
Requires-Python: <3.13,>=3.8
License-File: LICENSE
Requires-Dist: tree-sitter ==0.21.3
Requires-Dist: dataclasses-json <0.6,>=0.5.7
Provides-Extra: mypy
Requires-Dist: types-setuptools ; extra == 'mypy'
Provides-Extra: test
Requires-Dist: bumpver ; extra == 'test'
Requires-Dist: mypy <2,>=1.1.1 ; extra == 'test'
Requires-Dist: pytest <9,>=7.1.2 ; extra == 'test'
Requires-Dist: pytest-golden <0.3,>=0.2.2 ; extra == 'test'
Requires-Dist: setuptools >=45 ; extra == 'test'
